{
 "repo_name": "keenethics/svelte-notifications",
 "contributors": [
  {
   "type": "User",
   "id": "usernamus",
   "contributions": 107
  },
  {
   "type": "User",
   "id": "Art-auto",
   "contributions": 8
  },
  {
   "type": "User",
   "id": "vlad-elagin",
   "contributions": 5
  },
  {
   "type": "User",
   "id": "minggas",
   "contributions": 3
  },
  {
   "type": "User",
   "id": "IgVol",
   "contributions": 2
  },
  {
   "type": "Bot",
   "id": "dependabot[bot]",
   "contributions": 2
  },
  {
   "type": "User",
   "id": "goknsh",
   "contributions": 1
  },
  {
   "type": "User",
   "id": "albingroen",
   "contributions": 1
  },
  {
   "type": "User",
   "id": "albinmedoc",
   "contributions": 1
  },
  {
   "type": "User",
   "id": "d34dman",
   "contributions": 1
  },
  {
   "type": "User",
   "id": "demogoran",
   "contributions": 1
  },
  {
   "type": "User",
   "id": "CatchABus",
   "contributions": 1
  },
  {
   "type": "User",
   "id": "shaozi",
   "contributions": 1
  },
  {
   "type": "User",
   "id": "doolijb",
   "contributions": 1
  },
  {
   "type": "User",
   "id": "Notalama",
   "contributions": 1
  },
  {
   "type": "User",
   "id": "wkornks",
   "contributions": 1
  },
  {
   "type": "User",
   "id": "Rich-Harris",
   "contributions": 1
  },
  {
   "type": "User",
   "id": "axtn",
   "contributions": 1
  },
  {
   "type": "User",
   "id": "iczc",
   "contributions": 1
  },
  {
   "type": "User",
   "id": "winston0410",
   "contributions": 1
  }
 ]
}